ConsolePrint/__init__.py
ConsolePrint/animate.py
ConsolePrint/ansi.py
ConsolePrint/console2file.py
ConsolePrint/loading.py
ConsolePrint/logo.py
consoleprint-1.11.7.dist-info/METADATA
consoleprint-1.11.7.dist-info/WHEEL
consoleprint-1.11.7.dist-info/licenses/LICENSE
consoleprint-1.11.7.dist-info/RECORD
