Metadata-Version: 2.4
Name: ConsolePrint
Version: 1.11.7
Summary: A package that animates and adds colour to the terminal outputs and can be used to redirect the output to a file
Project-URL: Homepage, https://github.com/iloabachie/ConsolePrint
Project-URL: Bug Tracker, https://github.com/iloabachie/ConsolePrint/issues
Author-email: Udemezue Iloabachie <udemezue@gmail.com>
License-File: LICENSE
Classifier: License :: OSI Approved :: MIT License
Classifier: Operating System :: Microsoft :: Windows
Classifier: Operating System :: POSIX :: Linux
Classifier: Programming Language :: Python :: 3
Requires-Python: >=3.10
